pydecima/__init__.py
pydecima/_utils.py
pydecima/reader.py
pydecima/enums/DecimaVersion.py
pydecima/enums/EAudioLanguages.py
pydecima/enums/EPixelFormat.py
pydecima/enums/ESentenceGroupType.py
pydecima/enums/ETextLanguages.py
pydecima/enums/ETextureSetType.py
pydecima/enums/EWaveDataEncoding.py
pydecima/enums/EWaveDataEncodingQuality.py
pydecima/enums/__init__.py
pydecima/resources/AmmoResource.py
pydecima/resources/CharacterDescriptionComponentResource.py
pydecima/resources/CollisionTrigger.py
pydecima/resources/CreditsColumn.py
pydecima/resources/CreditsRow.py
pydecima/resources/DamageAreaResource.py
pydecima/resources/DataSourceCreditsResource.py
pydecima/resources/EntityProjectileAmmoResource.py
pydecima/resources/EntityResource.py
pydecima/resources/ExplosionResource.py
pydecima/resources/FacialAnimationComponentResource.py
pydecima/resources/FactCollisionTrigger.py
pydecima/resources/FocusScannedInfo.py
pydecima/resources/FocusTargetComponentResource.py
pydecima/resources/HumanoidBodyVariant.py
pydecima/resources/HumanoidBodyVariantGroup.py
pydecima/resources/InventoryActionAbilityResource.py
pydecima/resources/InventoryAmmoEjectorResource.py
pydecima/resources/InventoryEntityResource.py
pydecima/resources/InventoryItemComponentResource.py
pydecima/resources/InventoryLootPackageComponentResource.py
pydecima/resources/LocalizedAnimationResource.py
pydecima/resources/LocalizedSimpleSoundResource.py
pydecima/resources/LocalizedTextResource.py
pydecima/resources/LootData.py
pydecima/resources/LootItem.py
pydecima/resources/LootSlot.py
pydecima/resources/MusicResource.py
pydecima/resources/ObjectCollection.py
pydecima/resources/OutOfBoundsNavMeshArea.py
pydecima/resources/PhysicsCollisionResource.py
pydecima/resources/PrefetchList.py
pydecima/resources/Resource.py
pydecima/resources/SentenceGroupResource.py
pydecima/resources/SentenceResource.py
pydecima/resources/SkeletonAnimationResource.py
pydecima/resources/SpawnSetup.py
pydecima/resources/SpawnSetupGroup.py
pydecima-1.0.1.dist-info/LICENSE
pydecima-1.0.1.dist-info/METADATA
pydecima-1.0.1.dist-info/WHEEL
pydecima-1.0.1.dist-info/top_level.txt
pydecima-1.0.1.dist-info/RECORD
