Metadata-Version: 2.1
Name: pydecima
Version: 1.0.1
Summary: Tools for reading files from the Decima game engine.
Author: Bearborg
License: Copyright (c) 2022 Bearborg        
Project-URL: Homepage, https://github.com/Bearborg/pydecima
Project-URL: Bug Tracker, https://github.com/Bearborg/pydecima/issues
Classifier: Programming Language :: Python :: 3
Classifier: License :: OSI Approved :: MIT License
Classifier: Operating System :: OS Independent
Requires-Python: >=3.7
License-File: LICENSE
